itchatmphttp/__init__.py
itchatmphttp-0.0.1.dist-info/DESCRIPTION.rst
itchatmphttp-0.0.1.dist-info/METADATA
itchatmphttp-0.0.1.dist-info/RECORD
itchatmphttp-0.0.1.dist-info/WHEEL
itchatmphttp-0.0.1.dist-info/metadata.json
itchatmphttp-0.0.1.dist-info/top_level.txt
