Metadata-Version: 2.0
Name: itchatmphttp
Version: 0.0.1
Summary: A coroutine requests for wechat massive platfrom api project itchatmp
Home-page: https://github.com/littlecodersh/itchatmphttp
Author: LittleCoder
Author-email: i7meavnktqegm1b@qq.com
License: MIT
Keywords: wechat itchatmp api weixin massive platfrom requests
Platform: UNKNOWN
Classifier: Development Status :: 3 - Alpha
Classifier: Intended Audience :: Developers
Classifier: Topic :: Software Development :: Libraries :: Python Modules
Classifier: License :: OSI Approved :: MIT License
Classifier: Programming Language :: Python :: 2
Classifier: Programming Language :: Python :: 3
Requires-Dist: requests
Requires-Dist: tornado
